[
  {
    "id": 1,
    "name": "Casa",
    "category": "home"
  },
  {
    "id": 2,
    "name": "Sobrado",
    "category": "home"
  },
  {
    "id": 3,
    "name": "Quitinete",
    "category": "home"
  },
  {
    "id": 4,
    "name": "Chalé",
    "category": "home"
  },
  {
    "id": 5,
    "name": "Dupléx",
    "category": "home"
  },
  {
    "id": 6,
    "name": "Chácara",
    "category": "farm"
  },
  {
    "id": 7,
    "name": "Fazenda",
    "category": "farm"
  },
  {
    "id": 8,
    "name": "Terreno",
    "category": "land"
  },
  {
    "id": 9,
    "name": "Prédio",
    "category": "building"
  },
  {
    "id": 10,
    "name": "Apartamento",
    "category": "apartment"
  },
  {
    "id": 11,
    "name": "Loja comercial",
    "category": "store"
  },
  {
    "id": 12,
    "name": "Fabrica",
    "category": "factory"
  },
  {
    "id": 13,
    "name": "Mansão",
    "category": "home"
  },
  {
    "id": 14,
    "name": "Condomínio",
    "category": "condominium"
  },
  {
    "id": 15,
    "name": "Quarto",
    "category": "bedroom"
  },
  {
    "id": 16,
    "name": "Bloco",
    "category": "building"
  },
  {
    "id": 17,
    "name": "Sítio",
    "category": "farm"
  },
  {
    "id": 18,
    "name": "Barracão",
    "category": "building"
  },
  {
    "id": 19,
    "name": "Shopping",
    "category": "shopping"
  },
  {
    "id": 20,
    "name": "Galpão",
    "category": "building"
  },
  {
    "id": 21,
    "name": "Sala",
    "category": "home"
  },
  {
    "id": 22,
    "name": "Área",
    "category": "farm"
  },
  {
    "id": 23,
    "name": "Conjunto comercial",
    "category": "store"
  },
  {
    "id": 24,
    "name": "Tríplex",
    "category": "home"
  },
  {
    "id": 25,
    "name": "Flat",
    "category": "home"
  },
  {
    "id": 26,
    "name": "Loteamento",
    "category": "land"
  },
  {
    "id": 27,
    "name": "Pousada",
    "category": "home"
  },
  {
    "id": 28,
    "name": "Cobertura",
    "category": "apartment"
  }
]
